[
  {
    "id": "2d81a071-d76a-46f3-987f-d2fba23cc188",
    "created_at": "2026-05-25T11:04:22.815494+00:00",
    "student_data": {
      "anxiety_level": 14,
      "self_esteem": 20,
      "mental_health_history": 0,
      "depression": 11,
      "headache": 2,
      "sleep_quality": 2,
      "academic_performance": 3,
      "study_load": 2,
      "future_career_concerns": 3,
      "social_support": 2,
      "peer_pressure": 3,
      "bullying": 2,
      "Age": 22,
      "Total_App_Usage_Hours": 6.0,
      "Daily_Screen_Time_Hours": 7.0,
      "Number_of_Apps_Used": 16,
      "Social_Media_Usage_Hours": 3.0,
      "Productivity_App_Usage_Hours": 2.0,
      "Gaming_App_Usage_Hours": 2.0,
      "digital_overload_score": 14.0,
      "productivity_balance_score": 0.5,
      "study_stress_ratio": 1.0,
      "mental_risk_score": 30
    },
    "result": {
      "stress_level": 1,
      "stress_class": "Sedang",
      "confidence": 0.9417,
      "probabilities": {
        "rendah": 0.0407,
        "sedang": 0.9417,
        "tinggi": 0.0175
      },
      "recommendation": "Ada indikasi stres sedang. Coba kurangi screen time berlebih, rapikan beban belajar, dan sisihkan waktu istirahat yang konsisten.",
      "ai_advice": "Saran AI generatif belum aktif. Isi GROQ_API_KEY pada environment variable untuk mengaktifkannya."
    }
  },
  {
    "id": "a2afe49a-a2bb-4432-9b15-c8a532d2734d",
    "created_at": "2026-05-25T11:00:03.321625+00:00",
    "student_data": {
      "anxiety_level": 14,
      "self_esteem": 20,
      "mental_health_history": 0,
      "depression": 11,
      "headache": 2,
      "sleep_quality": 2,
      "academic_performance": 3,
      "study_load": 2,
      "future_career_concerns": 3,
      "social_support": 2,
      "peer_pressure": 3,
      "bullying": 2,
      "Age": 22,
      "Total_App_Usage_Hours": 6.0,
      "Daily_Screen_Time_Hours": 7.0,
      "Number_of_Apps_Used": 16,
      "Social_Media_Usage_Hours": 3.0,
      "Productivity_App_Usage_Hours": 2.0,
      "Gaming_App_Usage_Hours": 2.0,
      "digital_overload_score": 14.0,
      "productivity_balance_score": 0.5,
      "study_stress_ratio": 1.0,
      "mental_risk_score": 30
    },
    "result": {
      "stress_level": 1,
      "stress_class": "Sedang",
      "confidence": 0.9417,
      "probabilities": {
        "rendah": 0.0407,
        "sedang": 0.9417,
        "tinggi": 0.0175
      },
      "recommendation": "Ada indikasi stres sedang. Coba kurangi screen time berlebih, rapikan beban belajar, dan sisihkan waktu istirahat yang konsisten.",
      "ai_advice": "Saran AI generatif belum aktif. Isi GROQ_API_KEY pada environment variable untuk mengaktifkannya."
    }
  },
  {
    "id": "cf98a601-d1d3-4ad4-973d-94531fffded0",
    "created_at": "2026-05-25T10:53:44.946556+00:00",
    "student_data": {
      "anxiety_level": 19,
      "self_esteem": 15,
      "mental_health_history": 0,
      "depression": 7,
      "headache": 4,
      "sleep_quality": 5,
      "academic_performance": 5,
      "study_load": 5,
      "future_career_concerns": 5,
      "social_support": 1,
      "peer_pressure": 5,
      "bullying": 3,
      "Age": 25,
      "Total_App_Usage_Hours": 8.0,
      "Daily_Screen_Time_Hours": 7.0,
      "Number_of_Apps_Used": 16,
      "Social_Media_Usage_Hours": 3.0,
      "Productivity_App_Usage_Hours": 2.0,
      "Gaming_App_Usage_Hours": 2.0,
      "digital_overload_score": 14.0,
      "productivity_balance_score": 0.5,
      "study_stress_ratio": 1.2,
      "mental_risk_score": 32
    },
    "result": {
      "stress_level": 2,
      "stress_class": "Tinggi",
      "confidence": 0.5949,
      "probabilities": {
        "rendah": 0.1419,
        "sedang": 0.2632,
        "tinggi": 0.5949
      },
      "recommendation": "Indikasi stres tinggi terdeteksi. Evaluasi jadwal digital, kualitas tidur, dan pertimbangkan berbicara dengan dosen wali atau konselor kampus.",
      "ai_advice": "Saran AI generatif belum aktif. Isi GROQ_API_KEY pada environment variable untuk mengaktifkannya."
    }
  },
  {
    "id": "d89ea84b-c812-4fab-97aa-ef22460a68d8",
    "created_at": "2026-05-25T10:53:42.540036+00:00",
    "student_data": {
      "anxiety_level": 19,
      "self_esteem": 15,
      "mental_health_history": 0,
      "depression": 7,
      "headache": 4,
      "sleep_quality": 5,
      "academic_performance": 5,
      "study_load": 5,
      "future_career_concerns": 5,
      "social_support": 1,
      "peer_pressure": 5,
      "bullying": 3,
      "Age": 25,
      "Total_App_Usage_Hours": 8.0,
      "Daily_Screen_Time_Hours": 7.0,
      "Number_of_Apps_Used": 16,
      "Social_Media_Usage_Hours": 3.0,
      "Productivity_App_Usage_Hours": 2.0,
      "Gaming_App_Usage_Hours": 2.0,
      "digital_overload_score": 14.0,
      "productivity_balance_score": 0.5,
      "study_stress_ratio": 1.2,
      "mental_risk_score": 32
    },
    "result": {
      "stress_level": 2,
      "stress_class": "Tinggi",
      "confidence": 0.5949,
      "probabilities": {
        "rendah": 0.1419,
        "sedang": 0.2632,
        "tinggi": 0.5949
      },
      "recommendation": "Indikasi stres tinggi terdeteksi. Evaluasi jadwal digital, kualitas tidur, dan pertimbangkan berbicara dengan dosen wali atau konselor kampus.",
      "ai_advice": "Saran AI generatif belum aktif. Isi GROQ_API_KEY pada environment variable untuk mengaktifkannya."
    }
  }
]